scintilla/__init__.py
scintilla/dataframe_generator.py
scintilla-0.0.3.dist-info/METADATA
scintilla-0.0.3.dist-info/WHEEL
scintilla-0.0.3.dist-info/top_level.txt
scintilla-0.0.3.dist-info/RECORD
