Metadata-Version: 2.1
Name: scintilla
Version: 0.0.3
Summary: Scintilla - Generate DataFrames for property based testing
Home-page: https://github.com/goncaloccastro/scintilla
Author: Gonçalo Castro
Author-email: goncaloccastro@gmail.com
License: MIT
Platform: UNKNOWN
Requires-Python: >=3.7
